FridaySTT/__init__.py
FridaySTT-0.1.dist-info/METADATA
FridaySTT-0.1.dist-info/WHEEL
FridaySTT-0.1.dist-info/top_level.txt
FridaySTT-0.1.dist-info/RECORD
